twigs_host_benchmark/__init__.py
twigs_host_benchmark/lynis-3.0.8.tar.gz
twigs_host_benchmark/twigs_host_benchmark.py
twigs_host_benchmark/utils.py
twigs_host_benchmark-1.0.3.dist-info/AUTHORS.rst
twigs_host_benchmark-1.0.3.dist-info/LICENSE
twigs_host_benchmark-1.0.3.dist-info/METADATA
twigs_host_benchmark-1.0.3.dist-info/WHEEL
twigs_host_benchmark-1.0.3.dist-info/top_level.txt
twigs_host_benchmark-1.0.3.dist-info/RECORD
