Metadata-Version: 2.1
Name: twigs-host-benchmark
Version: 1.0.3
Summary: TWIGS Host Benchmark
Home-page: https://github.com/threawatch/twigs_host_benchmark
Author: Paresh Borkar
Author-email: opensource@threatwatch.io
License: GNU General Public License v3
Keywords: twigs_host_benchmark
Platform: UNKNOWN
Classifier: Development Status :: 2 - Pre-Alpha
Classifier: Intended Audience :: Developers
Classifier: License :: OSI Approved :: GNU General Public License v3 (GPLv3)
Classifier: Natural Language :: English
Classifier: Programming Language :: Python :: 2
Classifier: Programming Language :: Python :: 2.7
Classifier: Programming Language :: Python :: 3
Classifier: Programming Language :: Python :: 3.5
Classifier: Programming Language :: Python :: 3.6
Classifier: Programming Language :: Python :: 3.7
Classifier: Programming Language :: Python :: 3.8
Requires-Dist: paramiko (==2.6.0)
Requires-Dist: scp (==0.13.3)
